wagtailversesblock/__init__.py
wagtailversesblock/blocks.py
wagtailversesblock-1.0.0.dist-info/LICENSE
wagtailversesblock-1.0.0.dist-info/METADATA
wagtailversesblock-1.0.0.dist-info/WHEEL
wagtailversesblock-1.0.0.dist-info/top_level.txt
wagtailversesblock-1.0.0.dist-info/RECORD
